eiondb/__init__.py
eiondb/cli.py
eiondb/client.py
eiondb/exceptions.py
eiondb-0.1.4.dist-info/licenses/LICENSE
eiondb-0.1.4.dist-info/METADATA
eiondb-0.1.4.dist-info/WHEEL
eiondb-0.1.4.dist-info/entry_points.txt
eiondb-0.1.4.dist-info/top_level.txt
eiondb-0.1.4.dist-info/RECORD
